{
  "_fv": 69,
  "_type": "gui",
  "definition": {
    "type": 1,
    "width": 176,
    "height": 166,
    "inventoryOffsetX": 0,
    "inventoryOffsetY": 0,
    "renderBgLayer": true,
    "doesPauseGame": false,
    "components": [
      {
        "type": "inputslot",
        "data": {
          "inputLimit": {
            "value": ""
          },
          "disablePlacement": {
            "fixedValue": false
          },
          "id": 0,
          "disablePickup": {
            "fixedValue": false
          },
          "dropItemsWhenNotBound": false,
          "x": 187,
          "y": 53
        }
      },
      {
        "type": "inputslot",
        "data": {
          "inputLimit": {
            "value": ""
          },
          "disablePlacement": {
            "fixedValue": false
          },
          "id": 1,
          "disablePickup": {
            "fixedValue": false
          },
          "dropItemsWhenNotBound": true,
          "x": 205,
          "y": 53
        }
      },
      {
        "type": "inputslot",
        "data": {
          "inputLimit": {
            "value": ""
          },
          "disablePlacement": {
            "fixedValue": false
          },
          "id": 2,
          "disablePickup": {
            "fixedValue": false
          },
          "dropItemsWhenNotBound": true,
          "x": 223,
          "y": 53
        }
      },
      {
        "type": "inputslot",
        "data": {
          "inputLimit": {
            "value": ""
          },
          "disablePlacement": {
            "fixedValue": false
          },
          "id": 3,
          "disablePickup": {
            "fixedValue": false
          },
          "dropItemsWhenNotBound": true,
          "x": 187,
          "y": 71
        }
      },
      {
        "type": "inputslot",
        "data": {
          "inputLimit": {
            "value": ""
          },
          "disablePlacement": {
            "fixedValue": false
          },
          "id": 4,
          "disablePickup": {
            "fixedValue": false
          },
          "dropItemsWhenNotBound": true,
          "x": 205,
          "y": 71
        }
      },
      {
        "type": "inputslot",
        "data": {
          "inputLimit": {
            "value": ""
          },
          "disablePlacement": {
            "fixedValue": false
          },
          "id": 5,
          "disablePickup": {
            "fixedValue": false
          },
          "dropItemsWhenNotBound": true,
          "x": 223,
          "y": 71
        }
      },
      {
        "type": "inputslot",
        "data": {
          "inputLimit": {
            "value": ""
          },
          "disablePlacement": {
            "fixedValue": false
          },
          "id": 6,
          "disablePickup": {
            "fixedValue": false
          },
          "dropItemsWhenNotBound": true,
          "x": 187,
          "y": 89
        }
      },
      {
        "type": "inputslot",
        "data": {
          "inputLimit": {
            "value": ""
          },
          "disablePlacement": {
            "fixedValue": false
          },
          "id": 7,
          "disablePickup": {
            "fixedValue": false
          },
          "dropItemsWhenNotBound": true,
          "x": 205,
          "y": 89
        }
      },
      {
        "type": "inputslot",
        "data": {
          "inputLimit": {
            "value": ""
          },
          "disablePlacement": {
            "fixedValue": false
          },
          "id": 8,
          "disablePickup": {
            "fixedValue": false
          },
          "dropItemsWhenNotBound": true,
          "x": 223,
          "y": 89
        }
      },
      {
        "type": "label",
        "data": {
          "name": "label_safe_label",
          "text": {
            "fixedValue": "safe_label"
          },
          "color": {
            "value": -1,
            "falpha": 0.0
          },
          "x": 127,
          "y": 27
        }
      },
      {
        "type": "image",
        "data": {
          "image": "crown.png",
          "use1Xscale": false,
          "x": 265,
          "y": 25
        }
      },
      {
        "type": "tooltip",
        "data": {
          "name": "tooltip_safe_help",
          "text": {
            "fixedValue": "safe_help"
          },
          "width": 24,
          "height": 24,
          "x": 261,
          "y": 20
        }
      }
    ],
    "gridSettings": {
      "sx": 18,
      "sy": 18,
      "ox": 11,
      "oy": 15,
      "snapOnGrid": false
    }
  }
}